neo4j/_rust.cp311-win_amd64.pyd
neo4j_rust_ext-6.0.3.0.dist-info/METADATA
neo4j_rust_ext-6.0.3.0.dist-info/WHEEL
neo4j_rust_ext-6.0.3.0.dist-info/licenses/LICENSE.APACHE2.txt
neo4j_rust_ext-6.0.3.0.dist-info/licenses/LICENSE.MIT.txt
neo4j_rust_ext-6.0.3.0.dist-info/licenses/LICENSE.txt
neo4j_rust_ext-6.0.3.0.dist-info/RECORD
