Metadata-Version: 2.4
Name: neo4j-rust-ext
Version: 6.0.3.0
Classifier: Development Status :: 5 - Production/Stable
Classifier: Intended Audience :: Developers
Classifier: Operating System :: OS Independent
Classifier: Programming Language :: Python :: 3.10
Classifier: Programming Language :: Python :: 3.11
Classifier: Programming Language :: Python :: 3.12
Classifier: Programming Language :: Python :: 3.13
Classifier: Programming Language :: Rust
Classifier: Topic :: Database
Classifier: Topic :: Software Development
Requires-Dist: neo4j==6.0.3
Requires-Dist: neo4j[numpy] ; extra == 'numpy'
Requires-Dist: neo4j[pandas] ; extra == 'pandas'
Requires-Dist: neo4j[pyarrow] ; extra == 'pyarrow'
Provides-Extra: numpy
Provides-Extra: pandas
Provides-Extra: pyarrow
License-File: LICENSE.APACHE2.txt
License-File: LICENSE.MIT.txt
License-File: LICENSE.txt
Summary: Rust Extensions for a Faster Neo4j Bolt Driver for Python
Keywords: neo4j,graph,database
Author-email: "Neo4j, Inc." <drivers@neo4j.com>
License-Expression: Apache-2.0 AND MIT
Requires-Python: >=3.10
Project-URL: Homepage, https://neo4j.com/
Project-URL: Repository, https://github.com/neo4j/neo4j-python-driver-rust-ext
Project-URL: Issue Tracker, https://github.com/neo4j/neo4j-python-driver-rust-ext/issues
Project-URL: Changelog, https://github.com/neo4j/neo4j-python-driver-rust-ext/blob/HEAD/CHANGELOG.md
Project-URL: Forum, https://community.neo4j.com/c/drivers-stacks/python/
Project-URL: Discord, https://discord.com/invite/neo4j
